cvui/__init__.py
cvui/cvui.py
cvui-2.7b1.dist-info/METADATA
cvui-2.7b1.dist-info/RECORD
cvui-2.7b1.dist-info/WHEEL
cvui-2.7b1.dist-info/top_level.txt
