Metadata-Version: 2.1
Name: cvui
Version: 2.7b1
Summary: A (very) simple UI lib built on top of OpenCV drawing primitives
Home-page: https://github.com/dovyski/cvui
Author: Fernando Bevilacqua
Author-email: dovyski@gmail.com
License: MIT
Platform: UNKNOWN
Classifier: Development Status :: 4 - Beta
Classifier: Intended Audience :: Developers
Classifier: License :: OSI Approved :: MIT License
Classifier: Operating System :: OS Independent
Classifier: Natural Language :: English
Classifier: Programming Language :: Python :: 2
Classifier: Programming Language :: Python :: 2.7
Classifier: Programming Language :: Python :: 3
Classifier: Programming Language :: Python :: 3.4
Classifier: Programming Language :: Python :: 3.5
Classifier: Programming Language :: Python :: 3.6
Classifier: Topic :: Software Development :: User Interfaces
